pep505/__init__.py
pep505/_test.py
pep505/auto.py
pep505/hook.py
pep505/parser.py
pep505/test.py
pep505/pegen/__init__.py
pep505/pegen/parser.py
pep505/pegen/tokenizer.py
pep505-0.9.3.dist-info/LICENSE
pep505-0.9.3.dist-info/METADATA
pep505-0.9.3.dist-info/WHEEL
pep505-0.9.3.dist-info/top_level.txt
pep505-0.9.3.dist-info/RECORD
