Metadata-Version: 2.1
Name: pep505
Version: 0.9.3
Summary: PEP505 Polyfill (None-aware/null-coalescing operators)
Home-page: https://github.com/acaos/python-pep505
Author: Doug Swarin
Author-email: dswarin@gmail.com
License: MIT
Project-URL: Bug Tracker, https://github.com/acaos/python-pep505/issues
Platform: UNKNOWN
Classifier: Development Status :: 4 - Beta
Classifier: License :: OSI Approved :: MIT License
Classifier: Operating System :: OS Independent
Classifier: Programming Language :: Python :: 3
Classifier: Programming Language :: Python :: 3.8
Classifier: Programming Language :: Python :: 3.9
Classifier: Programming Language :: Python :: 3.10
Requires-Python: <3.11,>=3.8
License-File: LICENSE
Requires-Dist: parsinghook
